flake8_polyfill/__init__.py
flake8_polyfill/options.py
flake8_polyfill/stdin.py
flake8_polyfill/version.py
flake8_polyfill-1.0.1.dist-info/DESCRIPTION.rst
flake8_polyfill-1.0.1.dist-info/METADATA
flake8_polyfill-1.0.1.dist-info/RECORD
flake8_polyfill-1.0.1.dist-info/WHEEL
flake8_polyfill-1.0.1.dist-info/metadata.json
flake8_polyfill-1.0.1.dist-info/top_level.txt
