Metadata-Version: 1.1
Name: flake8-polyfill
Version: 1.0.1
Summary: Polyfill package for Flake8 plugins
Home-page: https://gitlab.com/pycqa/flake8
Author: Ian Cordasco
Author-email: graffatcolmingov@gmail.com
License: MIT
Platform: UNKNOWN
Classifier: Environment :: Console
Classifier: Framework :: Flake8
Classifier: Intended Audience :: Developers
Classifier: License :: OSI Approved :: MIT License
Classifier: Programming Language :: Python
Classifier: Programming Language :: Python :: 2
Classifier: Programming Language :: Python :: 2.7
Classifier: Programming Language :: Python :: 3
Classifier: Programming Language :: Python :: 3.4
Classifier: Programming Language :: Python :: 3.5
Classifier: Topic :: Software Development :: Libraries :: Python Modules
Classifier: Topic :: Software Development :: Quality Assurance
